README.md
setup.py
afohtim_cpp_code_convention_formatter/__init__.py
afohtim_cpp_code_convention_formatter/formatter.py
afohtim_cpp_code_convention_formatter/lexer.py
afohtim_cpp_code_convention_formatter/main.py
afohtim_cpp_code_convention_formatter.egg-info/PKG-INFO
afohtim_cpp_code_convention_formatter.egg-info/SOURCES.txt
afohtim_cpp_code_convention_formatter.egg-info/dependency_links.txt
afohtim_cpp_code_convention_formatter.egg-info/entry_points.txt
afohtim_cpp_code_convention_formatter.egg-info/top_level.txt