Metadata-Version: 1.2
Name: afohtim-cpp-code-convention-formatter
Version: 0.0.3
Summary: uni metaprogramming lab 2
Home-page: UNKNOWN
Author: Afohtim
Author-email: afohmouth@gmail.com
License: UNKNOWN
Platform: UNKNOWN
Requires-Python: >=3.6
